[
  {
    "id": 100,
    "nameKey": "fx_arrow",
    "aboveCharacter": false,
    "tint": 16777215,
    "frameRate": 1,
    "frameSize": 128,
    "bodySize": 128,
    "fromScale": 1,
    "toScale": 1,
    "fromY": 0,
    "toY": 0,
    "fromX": 0,
    "toX": 0,
    "fromAngle": 90,
    "toAngle": 90,
    "fromAlpha": 1,
    "toAlpha": 1,
    "yoyo": false,
    "duration": 1,
    "keyTime": 0.5,
    "repeat": -1,
    "url": "fx_arrow.png"
  },
  {
    "id": 101,
    "nameKey": "fx_arrow_01",
    "aboveCharacter": false,
    "tint": 16777215,
    "frameRate": 1,
    "frameSize": 128,
    "bodySize": 128,
    "fromScale": 1,
    "toScale": 1,
    "fromY": 0,
    "toY": 0,
    "fromX": 0,
    "toX": 0,
    "fromAngle": 90,
    "toAngle": 90,
    "fromAlpha": 1,
    "toAlpha": 1,
    "yoyo": false,
    "duration": 1,
    "keyTime": 0.5,
    "repeat": -1,
    "url": "fx_arrow_01.png"
  },
  {
    "id": 102,
    "nameKey": "fx_arrow_02",
    "aboveCharacter": false,
    "tint": 16777215,
    "frameRate": 1,
    "frameSize": 128,
    "bodySize": 128,
    "fromScale": 1,
    "toScale": 1,
    "fromY": 0,
    "toY": 0,
    "fromX": 0,
    "toX": 0,
    "fromAngle": 90,
    "toAngle": 90,
    "fromAlpha": 1,
    "toAlpha": 1,
    "yoyo": false,
    "duration": 1,
    "keyTime": 0.5,
    "repeat": -1,
    "url": "fx_arrow_02.png"
  },
  {
    "id": 103,
    "nameKey": "fx_arrow_03",
    "aboveCharacter": false,
    "tint": 16777215,
    "frameRate": 1,
    "frameSize": 128,
    "bodySize": 128,
    "fromScale": 1,
    "toScale": 1,
    "fromY": 0,
    "toY": 0,
    "fromX": 0,
    "toX": 0,
    "fromAngle": -270,
    "toAngle": 90,
    "fromAlpha": 1,
    "toAlpha": 1,
    "yoyo": false,
    "duration": 0.3,
    "keyTime": 0.3,
    "repeat": -1,
    "url": "fx_arrow_03.png"
  },
  {
    "id": 104,
    "nameKey": "fx_arrow_04",
    "aboveCharacter": false,
    "tint": 16777215,
    "frameRate": 1,
    "frameSize": 128,
    "bodySize": 128,
    "fromScale": 1,
    "toScale": 1,
    "fromY": 0,
    "toY": 0,
    "fromX": 0,
    "toX": 0,
    "fromAngle": 90,
    "toAngle": 90,
    "fromAlpha": 1,
    "toAlpha": 1,
    "yoyo": false,
    "duration": 1,
    "keyTime": 0.5,
    "repeat": -1,
    "url": "fx_arrow_04.png"
  },
  {
    "id": 105,
    "nameKey": "fx_arrow_05",
    "aboveCharacter": false,
    "tint": 16777215,
    "frameRate": 1,
    "frameSize": 128,
    "bodySize": 128,
    "fromScale": 1,
    "toScale": 1,
    "fromY": 0,
    "toY": 0,
    "fromX": 0,
    "toX": 0,
    "fromAngle": 90,
    "toAngle": 90,
    "fromAlpha": 1,
    "toAlpha": 1,
    "yoyo": false,
    "duration": 1,
    "keyTime": 0.5,
    "repeat": -1,
    "url": "fx_arrow_05.png"
  },
  {
    "id": 106,
    "nameKey": "fx_arrow_06",
    "aboveCharacter": false,
    "tint": 16777215,
    "frameRate": 1,
    "frameSize": 128,
    "bodySize": 128,
    "fromScale": 1,
    "toScale": 1,
    "fromY": 0,
    "toY": 0,
    "fromX": 0,
    "toX": 0,
    "fromAngle": 90,
    "toAngle": 90,
    "fromAlpha": 1,
    "toAlpha": 1,
    "yoyo": false,
    "duration": 1,
    "keyTime": 0.5,
    "repeat": -1,
    "url": "fx_arrow_06.png"
  },
  {
    "id": 107,
    "nameKey": "fx_arrow_07",
    "aboveCharacter": false,
    "tint": 16777215,
    "frameRate": 1,
    "frameSize": 128,
    "bodySize": 64,
    "fromScale": 1,
    "toScale": 1,
    "fromY": 0,
    "toY": 0,
    "fromX": 0,
    "toX": 0,
    "fromAngle": 90,
    "toAngle": 90,
    "fromAlpha": 1,
    "toAlpha": 1,
    "yoyo": false,
    "duration": 1,
    "keyTime": 0.5,
    "repeat": -1,
    "url": "fx_arrow_07.png"
  },
  {
    "id": 108,
    "nameKey": "fx_arrow_08",
    "aboveCharacter": false,
    "tint": 16777215,
    "frameRate": 1,
    "frameSize": 128,
    "bodySize": 128,
    "fromScale": 1,
    "toScale": 1,
    "fromY": 0,
    "toY": 0,
    "fromX": 0,
    "toX": 0,
    "fromAngle": 0,
    "toAngle": 0,
    "fromAlpha": 1,
    "toAlpha": 1,
    "yoyo": false,
    "duration": 1,
    "keyTime": 0,
    "repeat": -1,
    "url": "fx_arrow_08.png"
  },
  {
    "id": 109,
    "nameKey": "fx_arrow_09",
    "aboveCharacter": false,
    "tint": 16777215,
    "frameRate": 1,
    "frameSize": 128,
    "bodySize": 128,
    "fromScale": 1,
    "toScale": 1,
    "fromY": 0,
    "toY": 0,
    "fromX": 0,
    "toX": 0,
    "fromAngle": 0,
    "toAngle": 0,
    "fromAlpha": 1,
    "toAlpha": 1,
    "yoyo": false,
    "duration": 1,
    "keyTime": 0,
    "repeat": -1,
    "url": "fx_arrow_09.png"
  },
  {
    "id": 110,
    "nameKey": "fx_arrow_10",
    "aboveCharacter": false,
    "tint": 16777215,
    "frameRate": 1,
    "frameSize": 128,
    "bodySize": 128,
    "fromScale": 1,
    "toScale": 1,
    "fromY": 0,
    "toY": 0,
    "fromX": 0,
    "toX": 0,
    "fromAngle": 0,
    "toAngle": 0,
    "fromAlpha": 1,
    "toAlpha": 1,
    "yoyo": false,
    "duration": 1,
    "keyTime": 0,
    "repeat": -1,
    "url": "fx_arrow_10.png"
  },
  {
    "id": 111,
    "nameKey": "fx_arrow_11",
    "aboveCharacter": false,
    "tint": 16777215,
    "frameRate": 1,
    "frameSize": 128,
    "bodySize": 128,
    "fromScale": 1,
    "toScale": 1,
    "fromY": 0,
    "toY": 0,
    "fromX": 0,
    "toX": 0,
    "fromAngle": 0,
    "toAngle": 0,
    "fromAlpha": 1,
    "toAlpha": 1,
    "yoyo": false,
    "duration": 1,
    "keyTime": 0,
    "repeat": -1,
    "url": "fx_arrow_11.png"
  },
  {
    "id": 112,
    "nameKey": "fx_arrow_12",
    "aboveCharacter": false,
    "tint": 16777215,
    "frameRate": 1,
    "frameSize": 128,
    "bodySize": 128,
    "fromScale": 1,
    "toScale": 1,
    "fromY": 0,
    "toY": 0,
    "fromX": 0,
    "toX": 0,
    "fromAngle": 0,
    "toAngle": 0,
    "fromAlpha": 1,
    "toAlpha": 1,
    "yoyo": false,
    "duration": 1,
    "keyTime": 0,
    "repeat": -1,
    "url": "fx_arrow_12.png"
  },
  {
    "id": 113,
    "nameKey": "fx_arrow_13",
    "aboveCharacter": false,
    "tint": 16777215,
    "frameRate": 1,
    "frameSize": 128,
    "bodySize": 128,
    "fromScale": 1,
    "toScale": 1,
    "fromY": 0,
    "toY": 0,
    "fromX": 0,
    "toX": 0,
    "fromAngle": 0,
    "toAngle": 0,
    "fromAlpha": 1,
    "toAlpha": 1,
    "yoyo": false,
    "duration": 1,
    "keyTime": 0,
    "repeat": -1,
    "url": "fx_arrow_13.png"
  },
  {
    "id": 114,
    "nameKey": "fx_arrow_14",
    "aboveCharacter": false,
    "tint": 16777215,
    "frameRate": 1,
    "frameSize": 128,
    "bodySize": 128,
    "fromScale": 1,
    "toScale": 1,
    "fromY": 0,
    "toY": 0,
    "fromX": 0,
    "toX": 0,
    "fromAngle": -270,
    "toAngle": 90,
    "fromAlpha": 1,
    "toAlpha": 1,
    "yoyo": false,
    "duration": 0.3,
    "keyTime": 0.3,
    "repeat": -1,
    "url": "fx_arrow_14.png"
  },
  {
    "id": 115,
    "nameKey": "fx_arrow_15",
    "aboveCharacter": false,
    "tint": 16777215,
    "frameRate": 1,
    "frameSize": 128,
    "bodySize": 128,
    "fromScale": 1,
    "toScale": 1,
    "fromY": 0,
    "toY": 0,
    "fromX": 0,
    "toX": 0,
    "fromAngle": 0,
    "toAngle": 0,
    "fromAlpha": 1,
    "toAlpha": 1,
    "yoyo": false,
    "duration": 1,
    "keyTime": 0,
    "repeat": -1,
    "url": "fx_arrow_15.png"
  },
  {
    "id": 116,
    "nameKey": "fx_arrow_16",
    "aboveCharacter": false,
    "tint": 16777215,
    "frameRate": 1,
    "frameSize": 128,
    "bodySize": 128,
    "fromScale": 1,
    "toScale": 1,
    "fromY": 0,
    "toY": 0,
    "fromX": 0,
    "toX": 0,
    "fromAngle": 0,
    "toAngle": 0,
    "fromAlpha": 1,
    "toAlpha": 1,
    "yoyo": false,
    "duration": 1,
    "keyTime": 0,
    "repeat": -1,
    "url": "fx_arrow_16.png"
  },
  {
    "id": 200,
    "nameKey": "fx_blade",
    "aboveCharacter": false,
    "tint": 16777215,
    "frameRate": 1,
    "frameSize": 256,
    "bodySize": 256,
    "fromScale": 1,
    "toScale": 1,
    "fromY": 0,
    "toY": 0,
    "fromX": 0,
    "toX": 0,
    "fromAngle": -90,
    "toAngle": 90,
    "fromAlpha": 0,
    "toAlpha": 1,
    "yoyo": false,
    "duration": 0.2,
    "keyTime": 0.1,
    "repeat": 0,
    "url": "fx_blade.png"
  },
  {
    "id": 201,
    "nameKey": "fx_blade_01",
    "aboveCharacter": false,
    "tint": 16777215,
    "frameRate": 1,
    "frameSize": 256,
    "bodySize": 256,
    "fromScale": 1,
    "toScale": 1,
    "fromY": 0,
    "toY": 0,
    "fromX": 0,
    "toX": 0,
    "fromAngle": 90,
    "toAngle": -270,
    "fromAlpha": 1,
    "toAlpha": 1,
    "yoyo": true,
    "duration": 0.2,
    "keyTime": 0.2,
    "repeat": 0,
    "url": "fx_blade_01.png"
  },
  {
    "id": 202,
    "nameKey": "fx_blade_02",
    "aboveCharacter": false,
    "tint": 16777215,
    "frameRate": 1,
    "frameSize": 256,
    "bodySize": 256,
    "fromScale": 1,
    "toScale": 1,
    "fromY": 0,
    "toY": 0,
    "fromX": 0,
    "toX": 0,
    "fromAngle": -90,
    "toAngle": 90,
    "fromAlpha": 0,
    "toAlpha": 1,
    "yoyo": false,
    "duration": 0.2,
    "keyTime": 0.1,
    "repeat": 0,
    "url": "fx_blade_02.png"
  },
  {
    "id": 203,
    "nameKey": "fx_blade_03",
    "aboveCharacter": false,
    "tint": 16777215,
    "frameRate": 1,
    "frameSize": 256,
    "bodySize": 256,
    "fromScale": 1,
    "toScale": 1,
    "fromY": 0,
    "toY": 0,
    "fromX": 0,
    "toX": 0,
    "fromAngle": -270,
    "toAngle": 90,
    "fromAlpha": 1,
    "toAlpha": 1,
    "yoyo": false,
    "duration": 0.2,
    "keyTime": 0.1,
    "repeat": 0,
    "url": "fx_blade_03.png"
  },
  {
    "id": 204,
    "nameKey": "fx_blade_04",
    "aboveCharacter": false,
    "tint": 16777215,
    "frameRate": 1,
    "frameSize": 256,
    "bodySize": 256,
    "fromScale": 1,
    "toScale": 1,
    "fromY": 0,
    "toY": 0,
    "fromX": 0,
    "toX": 0,
    "fromAngle": -270,
    "toAngle": 90,
    "fromAlpha": 1,
    "toAlpha": 1,
    "yoyo": false,
    "duration": 1,
    "keyTime": 0,
    "repeat": -1,
    "url": "fx_blade_04.png"
  },
  {
    "id": 205,
    "nameKey": "fx_blade_05",
    "aboveCharacter": false,
    "tint": 16777215,
    "frameRate": 1,
    "frameSize": 256,
    "bodySize": 256,
    "fromScale": 1,
    "toScale": 1,
    "fromY": 0,
    "toY": 0,
    "fromX": 0,
    "toX": 0,
    "fromAngle": -270,
    "toAngle": 90,
    "fromAlpha": 1,
    "toAlpha": 1,
    "yoyo": false,
    "duration": 1,
    "keyTime": 0,
    "repeat": -1,
    "url": "fx_blade_05.png"
  },
  {
    "id": 301,
    "nameKey": "fx_buff_01",
    "aboveCharacter": true,
    "tint": 16777215,
    "frameRate": 1,
    "frameSize": 128,
    "bodySize": 128,
    "fromScale": 1,
    "toScale": 1,
    "fromY": 0,
    "toY": 0,
    "fromX": 0,
    "toX": 0,
    "fromAngle": 0,
    "toAngle": 0,
    "fromAlpha": 0,
    "toAlpha": 0,
    "yoyo": false,
    "duration": 1,
    "keyTime": 0.5,
    "repeat": 0,
    "url": "fx_buff_01.png"
  },
  {
    "id": 302,
    "nameKey": "fx_buff_02",
    "aboveCharacter": true,
    "tint": 16777215,
    "frameRate": 1,
    "frameSize": 128,
    "bodySize": 128,
    "fromScale": 1,
    "toScale": 1,
    "fromY": 0,
    "toY": 0,
    "fromX": 0,
    "toX": 0,
    "fromAngle": 0,
    "toAngle": 0,
    "fromAlpha": 0,
    "toAlpha": 0,
    "yoyo": false,
    "duration": 1,
    "keyTime": 0.5,
    "repeat": 0,
    "url": "fx_buff_02.png"
  },
  {
    "id": 303,
    "nameKey": "fx_buff_03",
    "aboveCharacter": true,
    "tint": 16777215,
    "frameRate": 1,
    "frameSize": 128,
    "bodySize": 128,
    "fromScale": 1,
    "toScale": 1,
    "fromY": 0,
    "toY": 0,
    "fromX": 0,
    "toX": 0,
    "fromAngle": -270,
    "toAngle": 90,
    "fromAlpha": 1,
    "toAlpha": 1,
    "yoyo": false,
    "duration": 1,
    "keyTime": 0.5,
    "repeat": -1,
    "url": "fx_buff_03.png"
  },
  {
    "id": 304,
    "nameKey": "fx_buff_04",
    "aboveCharacter": true,
    "tint": 16777215,
    "frameRate": 1,
    "frameSize": 128,
    "bodySize": 128,
    "fromScale": 0.9,
    "toScale": 1,
    "fromY": 0,
    "toY": 0,
    "fromX": 0,
    "toX": 0,
    "fromAngle": 90,
    "toAngle": 90,
    "fromAlpha": 0.3,
    "toAlpha": 1,
    "yoyo": true,
    "duration": 0.75,
    "keyTime": 0,
    "repeat": -1,
    "url": "fx_buff_04.png"
  },
  {
    "id": 305,
    "nameKey": "fx_buff_05",
    "aboveCharacter": true,
    "tint": 16777215,
    "frameRate": 1,
    "frameSize": 128,
    "bodySize": 128,
    "fromScale": 1,
    "toScale": 1,
    "fromY": 0,
    "toY": 0,
    "fromX": 0,
    "toX": 0,
    "fromAngle": -270,
    "toAngle": 90,
    "fromAlpha": 1,
    "toAlpha": 1,
    "yoyo": false,
    "duration": 1,
    "keyTime": 0,
    "repeat": -1,
    "url": "fx_buff_05.png"
  },
  {
    "id": 306,
    "nameKey": "fx_buff_06",
    "aboveCharacter": true,
    "tint": 16777215,
    "frameRate": 1,
    "frameSize": 128,
    "bodySize": 128,
    "fromScale": 1,
    "toScale": 1,
    "fromY": 0,
    "toY": 0,
    "fromX": 0,
    "toX": 0,
    "fromAngle": 90,
    "toAngle": 90,
    "fromAlpha": 0,
    "toAlpha": 0,
    "yoyo": false,
    "duration": 1,
    "keyTime": 0.5,
    "repeat": 0,
    "url": "fx_buff_06.png"
  },
  {
    "id": 307,
    "nameKey": "fx_buff_07",
    "aboveCharacter": true,
    "tint": 16777215,
    "frameRate": 1,
    "frameSize": 128,
    "bodySize": 128,
    "fromScale": 1,
    "toScale": 1,
    "fromY": 0,
    "toY": 0,
    "fromX": 0,
    "toX": 0,
    "fromAngle": 0,
    "toAngle": 0,
    "fromAlpha": 0,
    "toAlpha": 0,
    "yoyo": false,
    "duration": 1,
    "keyTime": 0.5,
    "repeat": 0,
    "url": "fx_buff_07.png"
  },
  {
    "id": 308,
    "nameKey": "fx_buff_08",
    "aboveCharacter": true,
    "tint": 16777215,
    "frameRate": 1,
    "frameSize": 128,
    "bodySize": 128,
    "fromScale": 1,
    "toScale": 1,
    "fromY": 0,
    "toY": 0,
    "fromX": 0,
    "toX": 0,
    "fromAngle": 0,
    "toAngle": 0,
    "fromAlpha": 1,
    "toAlpha": 1,
    "yoyo": false,
    "duration": 1,
    "keyTime": 0.5,
    "repeat": -1,
    "url": "fx_buff_08.png"
  },
  {
    "id": 309,
    "nameKey": "fx_buff_09",
    "aboveCharacter": true,
    "tint": 16777215,
    "frameRate": 1,
    "frameSize": 128,
    "bodySize": 128,
    "fromScale": 1.5,
    "toScale": 2,
    "fromY": -32,
    "toY": -32,
    "fromX": 0,
    "toX": 0,
    "fromAngle": 0,
    "toAngle": 0,
    "fromAlpha": 0.5,
    "toAlpha": 1,
    "yoyo": true,
    "duration": 0.3,
    "keyTime": 0.3,
    "repeat": 0,
    "url": "fx_buff_09.png"
  },
  {
    "id": 310,
    "nameKey": "fx_buff_10",
    "aboveCharacter": true,
    "tint": 16777215,
    "frameRate": 1,
    "frameSize": 128,
    "bodySize": 100,
    "fromScale": 1,
    "toScale": 1,
    "fromY": 0,
    "toY": 0,
    "fromX": 0,
    "toX": 0,
    "fromAngle": 90,
    "toAngle": 90,
    "fromAlpha": 1,
    "toAlpha": 1,
    "yoyo": false,
    "duration": 1,
    "keyTime": 0.5,
    "repeat": -1,
    "url": "fx_buff_10.png"
  },
  {
    "id": 311,
    "nameKey": "fx_buff_11",
    "aboveCharacter": true,
    "tint": 16777215,
    "frameRate": 1,
    "frameSize": 128,
    "bodySize": 128,
    "fromScale": 1,
    "toScale": 1,
    "fromY": 0,
    "toY": 0,
    "fromX": 0,
    "toX": 0,
    "fromAngle": 0,
    "toAngle": 0,
    "fromAlpha": 1,
    "toAlpha": 1,
    "yoyo": false,
    "duration": 1,
    "keyTime": 0.5,
    "repeat": -1,
    "url": "fx_buff_11.png"
  },
  {
    "id": 312,
    "nameKey": "fx_buff_12",
    "aboveCharacter": true,
    "tint": 16777215,
    "frameRate": 1,
    "frameSize": 128,
    "bodySize": 128,
    "fromScale": 1,
    "toScale": 1,
    "fromY": -80,
    "toY": -120,
    "fromX": 0,
    "toX": 0,
    "fromAngle": 0,
    "toAngle": 0,
    "fromAlpha": 0.8,
    "toAlpha": 1,
    "yoyo": false,
    "duration": 1,
    "keyTime": 0.5,
    "repeat": 0,
    "url": "fx_buff_12.png"
  },
  {
    "id": 313,
    "nameKey": "fx_buff_13",
    "aboveCharacter": true,
    "tint": 16777215,
    "frameRate": 1,
    "frameSize": 128,
    "bodySize": 128,
    "fromScale": 1,
    "toScale": 1,
    "fromY": -80,
    "toY": -120,
    "fromX": 0,
    "toX": 0,
    "fromAngle": 0,
    "toAngle": 0,
    "fromAlpha": 0.8,
    "toAlpha": 1,
    "yoyo": false,
    "duration": 1,
    "keyTime": 0.5,
    "repeat": 0,
    "url": "fx_buff_13.png"
  },
  {
    "id": 314,
    "nameKey": "fx_buff_14",
    "aboveCharacter": true,
    "tint": 16777215,
    "frameRate": 1,
    "frameSize": 128,
    "bodySize": 128,
    "fromScale": 1,
    "toScale": 1,
    "fromY": -80,
    "toY": -120,
    "fromX": 0,
    "toX": 0,
    "fromAngle": 0,
    "toAngle": 0,
    "fromAlpha": 0.8,
    "toAlpha": 1,
    "yoyo": false,
    "duration": 1,
    "keyTime": 0.5,
    "repeat": 0,
    "url": "fx_buff_14.png"
  },
  {
    "id": 315,
    "nameKey": "fx_buff_15",
    "aboveCharacter": true,
    "tint": 16777215,
    "frameRate": 1,
    "frameSize": 128,
    "bodySize": 128,
    "fromScale": 1,
    "toScale": 1,
    "fromY": -80,
    "toY": -120,
    "fromX": 0,
    "toX": 0,
    "fromAngle": 0,
    "toAngle": 0,
    "fromAlpha": 0.8,
    "toAlpha": 1,
    "yoyo": false,
    "duration": 1,
    "keyTime": 0.5,
    "repeat": 0,
    "url": "fx_buff_15.png"
  },
  {
    "id": 316,
    "nameKey": "fx_buff_16",
    "aboveCharacter": true,
    "tint": 16777215,
    "frameRate": 1,
    "frameSize": 128,
    "bodySize": 128,
    "fromScale": 0.5,
    "toScale": 0.5,
    "fromY": -80,
    "toY": -120,
    "fromX": 0,
    "toX": 0,
    "fromAngle": 0,
    "toAngle": 0,
    "fromAlpha": 0.8,
    "toAlpha": 1,
    "yoyo": false,
    "duration": 1,
    "keyTime": 0.5,
    "repeat": 0,
    "url": "fx_buff_16.png"
  },
  {
    "id": 317,
    "nameKey": "fx_buff_17",
    "aboveCharacter": true,
    "tint": 16777215,
    "frameRate": 1,
    "frameSize": 128,
    "bodySize": 128,
    "fromScale": 1,
    "toScale": 1,
    "fromY": -80,
    "toY": -120,
    "fromX": 0,
    "toX": 0,
    "fromAngle": 0,
    "toAngle": 0,
    "fromAlpha": 0.8,
    "toAlpha": 1,
    "yoyo": false,
    "duration": 1,
    "keyTime": 0.5,
    "repeat": 0,
    "url": "fx_buff_17.png"
  },
  {
    "id": 318,
    "nameKey": "fx_buff_18",
    "aboveCharacter": true,
    "tint": 16777215,
    "frameRate": 1,
    "frameSize": 128,
    "bodySize": 80,
    "fromScale": 1,
    "toScale": 1,
    "fromY": 0,
    "toY": 0,
    "fromX": 0,
    "toX": 0,
    "fromAngle": -270,
    "toAngle": 90,
    "fromAlpha": 1,
    "toAlpha": 1,
    "yoyo": false,
    "duration": 1,
    "keyTime": 0.5,
    "repeat": -1,
    "url": "fx_buff_18.png"
  },
  {
    "id": 319,
    "nameKey": "fx_buff_19",
    "aboveCharacter": true,
    "tint": 16777215,
    "frameRate": 1,
    "frameSize": 128,
    "bodySize": 128,
    "fromScale": 0,
    "toScale": 1,
    "fromY": 0,
    "toY": 0,
    "fromX": 0,
    "toX": 0,
    "fromAngle": 90,
    "toAngle": 90,
    "fromAlpha": 0,
    "toAlpha": 1,
    "yoyo": false,
    "duration": 0.25,
    "keyTime": 0.25,
    "repeat": 0,
    "url": "fx_buff_19.png"
  },
  {
    "id": 320,
    "nameKey": "fx_buff_20",
    "aboveCharacter": true,
    "tint": 16777215,
    "frameRate": 1,
    "frameSize": 128,
    "bodySize": 128,
    "fromScale": 1,
    "toScale": 1,
    "fromY": -120,
    "toY": -120,
    "fromX": 0,
    "toX": 0,
    "fromAngle": 0,
    "toAngle": 0,
    "fromAlpha": 0,
    "toAlpha": 1,
    "yoyo": true,
    "duration": 0.5,
    "keyTime": 0.5,
    "repeat": -1,
    "url": "fx_buff_20.png"
  },
  {
    "id": 321,
    "nameKey": "fx_buff_21",
    "aboveCharacter": true,
    "tint": 16777215,
    "frameRate": 1,
    "frameSize": 128,
    "bodySize": 128,
    "fromScale": 0.6,
    "toScale": 0.6,
    "fromY": 0,
    "toY": 0,
    "fromX": 0,
    "toX": 0,
    "fromAngle": 90,
    "toAngle": -270,
    "fromAlpha": 1,
    "toAlpha": 1,
    "yoyo": false,
    "duration": 0.5,
    "keyTime": 0.5,
    "repeat": -1,
    "url": "fx_buff_21.png"
  },
  {
    "id": 322,
    "nameKey": "fx_buff_22",
    "aboveCharacter": true,
    "tint": 16777215,
    "frameRate": 1,
    "frameSize": 128,
    "bodySize": 128,
    "fromScale": 1,
    "toScale": 1,
    "fromY": -120,
    "toY": -120,
    "fromX": 0,
    "toX": 0,
    "fromAngle": 0,
    "toAngle": 0,
    "fromAlpha": 0,
    "toAlpha": 1,
    "yoyo": true,
    "duration": 0.5,
    "keyTime": 0.5,
    "repeat": -1,
    "url": "fx_buff_22.png"
  },
  {
    "id": 323,
    "nameKey": "fx_buff_23",
    "aboveCharacter": true,
    "tint": 16777215,
    "frameRate": 1,
    "frameSize": 112,
    "bodySize": 112,
    "fromScale": 0.7,
    "toScale": 0.7,
    "fromY": -100,
    "toY": -90,
    "fromX": 0,
    "toX": 0,
    "fromAngle": 0,
    "toAngle": 0,
    "fromAlpha": 1,
    "toAlpha": 1,
    "yoyo": true,
    "duration": 0.5,
    "keyTime": 0.5,
    "repeat": -1,
    "url": "fx_buff_23.png"
  },
  {
    "id": 324,
    "nameKey": "fx_buff_24",
    "aboveCharacter": true,
    "tint": 16777215,
    "frameRate": 1,
    "frameSize": 128,
    "bodySize": 128,
    "fromScale": 1.2,
    "toScale": 1.2,
    "fromY": 0,
    "toY": 0,
    "fromX": 0,
    "toX": 0,
    "fromAngle": 0,
    "toAngle": 0,
    "fromAlpha": 1,
    "toAlpha": 1,
    "yoyo": false,
    "duration": 0.5,
    "keyTime": 0.5,
    "repeat": -1,
    "url": "fx_buff_24.png"
  },
  {
    "id": 325,
    "nameKey": "fx_buff_25",
    "aboveCharacter": false,
    "tint": 16777215,
    "frameRate": 16,
    "frameSize": 128,
    "bodySize": 128,
    "fromScale": 1,
    "toScale": 1,
    "fromY": 0,
    "toY": 0,
    "fromX": 0,
    "toX": 0,
    "fromAngle": 90,
    "toAngle": 90,
    "fromAlpha": 1,
    "toAlpha": 1,
    "yoyo": false,
    "duration": 1,
    "keyTime": 0.5,
    "repeat": -1,
    "url": "fx_buff_25.png"
  },
  {
    "id": 326,
    "nameKey": "fx_buff_26",
    "aboveCharacter": true,
    "tint": 16777215,
    "frameRate": 1,
    "frameSize": 128,
    "bodySize": 128,
    "fromScale": 0.8,
    "toScale": 1,
    "fromY": 0,
    "toY": 0,
    "fromX": 0,
    "toX": 0,
    "fromAngle": 0,
    "toAngle": 0,
    "fromAlpha": 0,
    "toAlpha": 1,
    "yoyo": true,
    "duration": 0.5,
    "keyTime": 0.5,
    "repeat": -1,
    "url": "fx_buff_26.png"
  },
  {
    "id": 327,
    "nameKey": "fx_buff_27",
    "aboveCharacter": true,
    "tint": 16777215,
    "frameRate": 10,
    "frameSize": 128,
    "bodySize": 128,
    "fromScale": 1,
    "toScale": 1,
    "fromY": 0,
    "toY": 0,
    "fromX": 0,
    "toX": 0,
    "fromAngle": 0,
    "toAngle": 0,
    "fromAlpha": 1,
    "toAlpha": 1,
    "yoyo": false,
    "duration": 0.7,
    "keyTime": 0,
    "repeat": -1,
    "url": "fx_buff_27.png"
  },
  {
    "id": 328,
    "nameKey": "fx_buff_28",
    "aboveCharacter": false,
    "tint": 16777215,
    "frameRate": 10,
    "frameSize": 128,
    "bodySize": 128,
    "fromScale": 1,
    "toScale": 1,
    "fromY": -100,
    "toY": -100,
    "fromX": 0,
    "toX": 0,
    "fromAngle": 0,
    "toAngle": 0,
    "fromAlpha": 1,
    "toAlpha": 1,
    "yoyo": false,
    "duration": 0.7,
    "keyTime": 0,
    "repeat": 0,
    "url": "fx_buff_28.png"
  },
  {
    "id": 329,
    "nameKey": "fx_buff_29",
    "aboveCharacter": true,
    "tint": 16777215,
    "frameRate": 10,
    "frameSize": 128,
    "bodySize": 128,
    "fromScale": 1,
    "toScale": 1,
    "fromY": 0,
    "toY": 0,
    "fromX": 0,
    "toX": 0,
    "fromAngle": 0,
    "toAngle": 0,
    "fromAlpha": 1,
    "toAlpha": 1,
    "yoyo": false,
    "duration": 0.7,
    "keyTime": 0,
    "repeat": -1,
    "url": "fx_buff_29.png"
  },
  {
    "id": 330,
    "nameKey": "fx_buff_30",
    "aboveCharacter": false,
    "tint": 16777215,
    "frameRate": 10,
    "frameSize": 128,
    "bodySize": 128,
    "fromScale": 1,
    "toScale": 1,
    "fromY": -100,
    "toY": -100,
    "fromX": 0,
    "toX": 0,
    "fromAngle": 0,
    "toAngle": 0,
    "fromAlpha": 1,
    "toAlpha": 1,
    "yoyo": false,
    "duration": 0.7,
    "keyTime": 0,
    "repeat": 0,
    "url": "fx_buff_30.png"
  },
  {
    "id": 331,
    "nameKey": "fx_buff_31",
    "aboveCharacter": true,
    "tint": 16777215,
    "frameRate": 10,
    "frameSize": 128,
    "bodySize": 128,
    "fromScale": 1,
    "toScale": 1,
    "fromY": 0,
    "toY": 0,
    "fromX": 0,
    "toX": 0,
    "fromAngle": 0,
    "toAngle": 0,
    "fromAlpha": 1,
    "toAlpha": 1,
    "yoyo": false,
    "duration": 0.7,
    "keyTime": 0,
    "repeat": -1,
    "url": "fx_buff_31.png"
  },
  {
    "id": 332,
    "nameKey": "fx_buff_32",
    "aboveCharacter": false,
    "tint": 16777215,
    "frameRate": 10,
    "frameSize": 128,
    "bodySize": 128,
    "fromScale": 1,
    "toScale": 1,
    "fromY": -100,
    "toY": -100,
    "fromX": 0,
    "toX": 0,
    "fromAngle": 0,
    "toAngle": 0,
    "fromAlpha": 1,
    "toAlpha": 1,
    "yoyo": false,
    "duration": 0.7,
    "keyTime": 0,
    "repeat": 0,
    "url": "fx_buff_32.png"
  },
  {
    "id": 333,
    "nameKey": "fx_buff_33",
    "aboveCharacter": true,
    "tint": 16777215,
    "frameRate": 10,
    "frameSize": 128,
    "bodySize": 128,
    "fromScale": 1,
    "toScale": 1,
    "fromY": 0,
    "toY": 0,
    "fromX": 0,
    "toX": 0,
    "fromAngle": 0,
    "toAngle": 0,
    "fromAlpha": 1,
    "toAlpha": 1,
    "yoyo": false,
    "duration": 0.7,
    "keyTime": 0,
    "repeat": -1,
    "url": "fx_buff_33.png"
  },
  {
    "id": 334,
    "nameKey": "fx_buff_34",
    "aboveCharacter": false,
    "tint": 16777215,
    "frameRate": 10,
    "frameSize": 128,
    "bodySize": 128,
    "fromScale": 1,
    "toScale": 1,
    "fromY": -100,
    "toY": -100,
    "fromX": 0,
    "toX": 0,
    "fromAngle": 0,
    "toAngle": 0,
    "fromAlpha": 1,
    "toAlpha": 1,
    "yoyo": false,
    "duration": 0.7,
    "keyTime": 0,
    "repeat": 0,
    "url": "fx_buff_34.png"
  },
  {
    "id": 335,
    "nameKey": "fx_buff_35",
    "aboveCharacter": true,
    "tint": 16777215,
    "frameRate": 10,
    "frameSize": 128,
    "bodySize": 128,
    "fromScale": 1,
    "toScale": 1,
    "fromY": 0,
    "toY": 0,
    "fromX": 0,
    "toX": 0,
    "fromAngle": 0,
    "toAngle": 0,
    "fromAlpha": 1,
    "toAlpha": 1,
    "yoyo": false,
    "duration": 0.7,
    "keyTime": 0,
    "repeat": -1,
    "url": "fx_buff_35.png"
  },
  {
    "id": 336,
    "nameKey": "fx_buff_36",
    "aboveCharacter": false,
    "tint": 16777215,
    "frameRate": 10,
    "frameSize": 128,
    "bodySize": 128,
    "fromScale": 1,
    "toScale": 1,
    "fromY": -100,
    "toY": -100,
    "fromX": 0,
    "toX": 0,
    "fromAngle": 0,
    "toAngle": 0,
    "fromAlpha": 1,
    "toAlpha": 1,
    "yoyo": false,
    "duration": 0.7,
    "keyTime": 0,
    "repeat": 0,
    "url": "fx_buff_36.png"
  },
  {
    "id": 337,
    "nameKey": "fx_buff_37",
    "aboveCharacter": true,
    "tint": 16777215,
    "frameRate": 10,
    "frameSize": 128,
    "bodySize": 128,
    "fromScale": 1,
    "toScale": 1,
    "fromY": 0,
    "toY": 0,
    "fromX": 0,
    "toX": 0,
    "fromAngle": 0,
    "toAngle": 0,
    "fromAlpha": 1,
    "toAlpha": 1,
    "yoyo": false,
    "duration": 0.7,
    "keyTime": 0,
    "repeat": -1,
    "url": "fx_buff_37.png"
  },
  {
    "id": 338,
    "nameKey": "fx_buff_38",
    "aboveCharacter": false,
    "tint": 16777215,
    "frameRate": 10,
    "frameSize": 128,
    "bodySize": 128,
    "fromScale": 1,
    "toScale": 1,
    "fromY": -100,
    "toY": -100,
    "fromX": 0,
    "toX": 0,
    "fromAngle": 0,
    "toAngle": 0,
    "fromAlpha": 1,
    "toAlpha": 1,
    "yoyo": false,
    "duration": 0.7,
    "keyTime": 0,
    "repeat": 0,
    "url": "fx_buff_38.png"
  },
  {
    "id": 339,
    "nameKey": "fx_buff_39",
    "aboveCharacter": true,
    "tint": 16777215,
    "frameRate": 1,
    "frameSize": 128,
    "bodySize": 128,
    "fromScale": 0.5,
    "toScale": 0.5,
    "fromY": -80,
    "toY": -120,
    "fromX": 0,
    "toX": 0,
    "fromAngle": 0,
    "toAngle": 0,
    "fromAlpha": 0.8,
    "toAlpha": 1,
    "yoyo": false,
    "duration": 1,
    "keyTime": 0.5,
    "repeat": 0,
    "url": "fx_buff_39.png"
  },
  {
    "id": 340,
    "nameKey": "fx_buff_40",
    "aboveCharacter": true,
    "tint": 16777215,
    "frameRate": 1,
    "frameSize": 128,
    "bodySize": 128,
    "fromScale": 0.5,
    "toScale": 0.5,
    "fromY": -80,
    "toY": -120,
    "fromX": 0,
    "toX": 0,
    "fromAngle": 0,
    "toAngle": 0,
    "fromAlpha": 0.8,
    "toAlpha": 1,
    "yoyo": false,
    "duration": 1,
    "keyTime": 0.5,
    "repeat": 0,
    "url": "fx_buff_40.png"
  },
  {
    "id": 341,
    "nameKey": "fx_buff_41",
    "aboveCharacter": false,
    "tint": 16777215,
    "frameRate": 10,
    "frameSize": 128,
    "bodySize": 128,
    "fromScale": 0.8,
    "toScale": 1,
    "fromY": 0,
    "toY": 0,
    "fromX": 20,
    "toX": -20,
    "fromAngle": 0,
    "toAngle": 0,
    "fromAlpha": 0.4,
    "toAlpha": 1,
    "yoyo": false,
    "duration": 1.2,
    "keyTime": 0,
    "repeat": 0,
    "url": "fx_buff_41.png"
  },
  {
    "id": 342,
    "nameKey": "fx_buff_42",
    "aboveCharacter": false,
    "tint": 16777215,
    "frameRate": 10,
    "frameSize": 128,
    "bodySize": 128,
    "fromScale": 0.8,
    "toScale": 1,
    "fromY": 0,
    "toY": 0,
    "fromX": -20,
    "toX": 20,
    "fromAngle": 0,
    "toAngle": 0,
    "fromAlpha": 0.4,
    "toAlpha": 1,
    "yoyo": false,
    "duration": 1.2,
    "keyTime": 0,
    "repeat": 0,
    "url": "fx_buff_42.png"
  },
  {
    "id": 343,
    "nameKey": "fx_buff_43",
    "aboveCharacter": true,
    "tint": 16777215,
    "frameRate": 1,
    "frameSize": 128,
    "bodySize": 80,
    "fromScale": 1,
    "toScale": 1,
    "fromY": 0,
    "toY": 0,
    "fromX": 0,
    "toX": 0,
    "fromAngle": -270,
    "toAngle": 90,
    "fromAlpha": 1,
    "toAlpha": 1,
    "yoyo": false,
    "duration": 1,
    "keyTime": 0.5,
    "repeat": -1,
    "url": "fx_buff_43.png"
  },
  {
    "id": 344,
    "nameKey": "fx_buff_44",
    "aboveCharacter": true,
    "tint": 16777215,
    "frameRate": 1,
    "frameSize": 128,
    "bodySize": 128,
    "fromScale": 0.5,
    "toScale": 0.5,
    "fromY": -80,
    "toY": -120,
    "fromX": 0,
    "toX": 0,
    "fromAngle": 0,
    "toAngle": 0,
    "fromAlpha": 0.8,
    "toAlpha": 1,
    "yoyo": false,
    "duration": 1,
    "keyTime": 0.5,
    "repeat": 0,
    "url": "fx_buff_44.png"
  },
  {
    "id": 345,
    "nameKey": "fx_buff_45",
    "aboveCharacter": true,
    "tint": 16777215,
    "frameRate": 1,
    "frameSize": 128,
    "bodySize": 128,
    "fromScale": 1.2,
    "toScale": 1.2,
    "fromY": 0,
    "toY": 0,
    "fromX": 0,
    "toX": 0,
    "fromAngle": 0,
    "toAngle": 0,
    "fromAlpha": 1,
    "toAlpha": 1,
    "yoyo": false,
    "duration": 1,
    "keyTime": 0.5,
    "repeat": -1,
    "url": "fx_buff_45.png"
  },
  {
    "id": 346,
    "nameKey": "fx_buff_46",
    "aboveCharacter": true,
    "tint": 16777215,
    "frameRate": 1,
    "frameSize": 128,
    "bodySize": 128,
    "fromScale": 1,
    "toScale": 1,
    "fromY": 0,
    "toY": 0,
    "fromX": 0,
    "toX": 0,
    "fromAngle": 0,
    "toAngle": 0,
    "fromAlpha": 1,
    "toAlpha": 1,
    "yoyo": false,
    "duration": 1,
    "keyTime": 0.5,
    "repeat": -1,
    "url": "fx_buff_46.png"
  },
  {
    "id": 347,
    "nameKey": "fx_buff_47",
    "aboveCharacter": true,
    "tint": 16777215,
    "frameRate": 20,
    "frameSize": 110,
    "bodySize": 110,
    "fromScale": 1,
    "toScale": 1,
    "fromY": 0,
    "toY": 0,
    "fromX": 0,
    "toX": 0,
    "fromAngle": 0,
    "toAngle": 0,
    "fromAlpha": 1,
    "toAlpha": 1,
    "yoyo": false,
    "duration": 0.5,
    "keyTime": 0.5,
    "repeat": 0,
    "url": "fx_buff_47.png"
  },
  {
    "id": 400,
    "nameKey": "fx_magic_org",
    "aboveCharacter": false,
    "tint": 16777215,
    "frameRate": 1,
    "frameSize": 128,
    "bodySize": 80,
    "fromScale": 1,
    "toScale": 1,
    "fromY": 0,
    "toY": 0,
    "fromX": 0,
    "toX": 0,
    "fromAngle": -270,
    "toAngle": 90,
    "fromAlpha": 1,
    "toAlpha": 1,
    "yoyo": false,
    "duration": 1,
    "keyTime": 0.5,
    "repeat": -1,
    "url": "fx_magic_org.png"
  },
  {
    "id": 401,
    "nameKey": "fx_magic_org_01",
    "aboveCharacter": false,
    "tint": 16777215,
    "frameRate": 1,
    "frameSize": 128,
    "bodySize": 80,
    "fromScale": 1,
    "toScale": 1,
    "fromY": 0,
    "toY": 0,
    "fromX": 0,
    "toX": 0,
    "fromAngle": -270,
    "toAngle": 90,
    "fromAlpha": 1,
    "toAlpha": 1,
    "yoyo": false,
    "duration": 1,
    "keyTime": 0.5,
    "repeat": -1,
    "url": "fx_magic_org_01.png"
  },
  {
    "id": 402,
    "nameKey": "fx_magic_org_02",
    "aboveCharacter": false,
    "tint": 16777215,
    "frameRate": 1,
    "frameSize": 128,
    "bodySize": 80,
    "fromScale": 1,
    "toScale": 1,
    "fromY": 0,
    "toY": 0,
    "fromX": 0,
    "toX": 0,
    "fromAngle": -90,
    "toAngle": -90,
    "fromAlpha": 1,
    "toAlpha": 1,
    "yoyo": false,
    "duration": 1,
    "keyTime": 0.5,
    "repeat": -1,
    "url": "fx_magic_org_02.png"
  },
  {
    "id": 403,
    "nameKey": "fx_magic_org_03",
    "aboveCharacter": false,
    "tint": 16777215,
    "frameRate": 1,
    "frameSize": 128,
    "bodySize": 80,
    "fromScale": 1,
    "toScale": 1,
    "fromY": 0,
    "toY": 0,
    "fromX": 0,
    "toX": 0,
    "fromAngle": -270,
    "toAngle": 90,
    "fromAlpha": 1,
    "toAlpha": 1,
    "yoyo": false,
    "duration": 1,
    "keyTime": 0.5,
    "repeat": -1,
    "url": "fx_magic_org_03.png"
  },
  {
    "id": 404,
    "nameKey": "fx_magic_org_04",
    "aboveCharacter": false,
    "tint": 16777215,
    "frameRate": 1,
    "frameSize": 128,
    "bodySize": 80,
    "fromScale": 1,
    "toScale": 1,
    "fromY": 0,
    "toY": 0,
    "fromX": 0,
    "toX": 0,
    "fromAngle": -270,
    "toAngle": 90,
    "fromAlpha": 1,
    "toAlpha": 1,
    "yoyo": false,
    "duration": 1,
    "keyTime": 0.5,
    "repeat": -1,
    "url": "fx_magic_org_04.png"
  },
  {
    "id": 405,
    "nameKey": "fx_magic_org_05",
    "aboveCharacter": false,
    "tint": 16777215,
    "frameRate": 1,
    "frameSize": 128,
    "bodySize": 20,
    "fromScale": 1,
    "toScale": 1,
    "fromY": 0,
    "toY": 0,
    "fromX": 0,
    "toX": 0,
    "fromAngle": 90,
    "toAngle": 90,
    "fromAlpha": 1,
    "toAlpha": 1,
    "yoyo": false,
    "duration": 1,
    "keyTime": 0.5,
    "repeat": -1,
    "url": "fx_magic_org_05.png"
  },
  {
    "id": 406,
    "nameKey": "fx_magic_org_06",
    "aboveCharacter": false,
    "tint": 16777215,
    "frameRate": 1,
    "frameSize": 128,
    "bodySize": 80,
    "fromScale": 1,
    "toScale": 1,
    "fromY": 0,
    "toY": 0,
    "fromX": 0,
    "toX": 0,
    "fromAngle": -270,
    "toAngle": 90,
    "fromAlpha": 1,
    "toAlpha": 1,
    "yoyo": false,
    "duration": 1,
    "keyTime": 0.5,
    "repeat": -1,
    "url": "fx_magic_org_06.png"
  },
  {
    "id": 407,
    "nameKey": "fx_magic_org_07",
    "aboveCharacter": false,
    "tint": 16777215,
    "frameRate": 1,
    "frameSize": 128,
    "bodySize": 128,
    "fromScale": 1,
    "toScale": 1,
    "fromY": 0,
    "toY": 0,
    "fromX": 0,
    "toX": 0,
    "fromAngle": 0,
    "toAngle": 0,
    "fromAlpha": 1,
    "toAlpha": 1,
    "yoyo": false,
    "duration": 1,
    "keyTime": 0,
    "repeat": -1,
    "url": "fx_magic_org_07.png"
  },
  {
    "id": 500,
    "nameKey": "fx_magic_ground",
    "aboveCharacter": false,
    "tint": 16777215,
    "frameRate": 1,
    "frameSize": 256,
    "bodySize": 218,
    "fromScale": 0.8,
    "toScale": 1,
    "fromY": 0,
    "toY": 0,
    "fromX": 0,
    "toX": 0,
    "fromAngle": 0,
    "toAngle": 0,
    "fromAlpha": 0.6,
    "toAlpha": 1,
    "yoyo": true,
    "duration": 0.2,
    "keyTime": 0.2,
    "repeat": 0,
    "url": "fx_magic_ground.png"
  },
  {
    "id": 501,
    "nameKey": "fx_magic_ground_01",
    "aboveCharacter": false,
    "tint": 16777215,
    "frameRate": 1,
    "frameSize": 256,
    "bodySize": 218,
    "fromScale": 0.8,
    "toScale": 1,
    "fromY": 0,
    "toY": 0,
    "fromX": 0,
    "toX": 0,
    "fromAngle": 0,
    "toAngle": 0,
    "fromAlpha": 0.6,
    "toAlpha": 1,
    "yoyo": true,
    "duration": 0.2,
    "keyTime": 0.2,
    "repeat": 0,
    "url": "fx_magic_ground_01.png"
  },
  {
    "id": 502,
    "nameKey": "fx_magic_ground_02",
    "aboveCharacter": false,
    "tint": 16777215,
    "frameRate": 1,
    "frameSize": 256,
    "bodySize": 128,
    "fromScale": 0.8,
    "toScale": 1,
    "fromY": 0,
    "toY": 0,
    "fromX": 0,
    "toX": 0,
    "fromAngle": 0,
    "toAngle": 0,
    "fromAlpha": 0.3,
    "toAlpha": 1,
    "yoyo": true,
    "duration": 0.3,
    "keyTime": 0,
    "repeat": 0,
    "url": "fx_magic_ground_02.png"
  },
  {
    "id": 503,
    "nameKey": "fx_magic_ground_03",
    "aboveCharacter": false,
    "tint": 16777215,
    "frameRate": 1,
    "frameSize": 128,
    "bodySize": 64,
    "fromScale": 0.8,
    "toScale": 1,
    "fromY": 0,
    "toY": 0,
    "fromX": 0,
    "toX": 0,
    "fromAngle": 0,
    "toAngle": 0,
    "fromAlpha": 0.6,
    "toAlpha": 1,
    "yoyo": true,
    "duration": 0.3,
    "keyTime": 0,
    "repeat": 0,
    "url": "fx_magic_ground_03.png"
  },
  {
    "id": 504,
    "nameKey": "fx_magic_ground_04",
    "aboveCharacter": false,
    "tint": 16777215,
    "frameRate": 1,
    "frameSize": 256,
    "bodySize": 218,
    "fromScale": 1,
    "toScale": 1,
    "fromY": 0,
    "toY": 0,
    "fromX": 0,
    "toX": 0,
    "fromAngle": 0,
    "toAngle": 0,
    "fromAlpha": 1,
    "toAlpha": 1,
    "yoyo": true,
    "duration": 0.2,
    "keyTime": 0.2,
    "repeat": -1,
    "url": "fx_magic_ground_04.png"
  },
  {
    "id": 505,
    "nameKey": "fx_magic_ground_05",
    "aboveCharacter": false,
    "tint": 16777215,
    "frameRate": 1,
    "frameSize": 128,
    "bodySize": 128,
    "fromScale": 1,
    "toScale": 1,
    "fromY": 0,
    "toY": 0,
    "fromX": 0,
    "toX": 0,
    "fromAngle": -90,
    "toAngle": 270,
    "fromAlpha": 1,
    "toAlpha": 1,
    "yoyo": false,
    "duration": 1,
    "keyTime": 0,
    "repeat": -1,
    "url": "fx_magic_ground_05.png"
  },
  {
    "id": 600,
    "nameKey": "fx_fire",
    "aboveCharacter": true,
    "tint": 16777215,
    "frameRate": 10,
    "frameSize": 128,
    "bodySize": 128,
    "fromScale": 1,
    "toScale": 1,
    "fromY": 0,
    "toY": 0,
    "fromX": 0,
    "toX": 0,
    "fromAngle": 0,
    "toAngle": 0,
    "fromAlpha": 1,
    "toAlpha": 1,
    "yoyo": false,
    "duration": 1,
    "keyTime": 1,
    "repeat": -1,
    "url": "fx_fire.png"
  },
  {
    "id": 601,
    "nameKey": "fx_explode",
    "aboveCharacter": true,
    "tint": 16777215,
    "frameRate": 44,
    "frameSize": 128,
    "bodySize": 128,
    "fromScale": 1,
    "toScale": 1,
    "fromY": 0,
    "toY": 0,
    "fromX": 0,
    "toX": 0,
    "fromAngle": 90,
    "toAngle": 90,
    "fromAlpha": 1,
    "toAlpha": 1,
    "yoyo": false,
    "duration": 0.3,
    "keyTime": 0.3,
    "repeat": 0,
    "url": "fx_explode.png"
  },
  {
    "id": 602,
    "nameKey": "fx_shine",
    "aboveCharacter": true,
    "tint": 16777215,
    "frameRate": 28,
    "frameSize": 256,
    "bodySize": 256,
    "fromScale": 2,
    "toScale": 2,
    "fromY": 0,
    "toY": 0,
    "fromX": 0,
    "toX": 0,
    "fromAngle": 90,
    "toAngle": 90,
    "fromAlpha": 1,
    "toAlpha": 1,
    "yoyo": false,
    "duration": 0.5,
    "keyTime": 0.5,
    "repeat": 0,
    "url": "fx_shine.png"
  },
  {
    "id": 701,
    "nameKey": "fx_avatar",
    "aboveCharacter": true,
    "tint": 16777215,
    "frameRate": 10,
    "frameSize": 128,
    "bodySize": 128,
    "fromScale": 1,
    "toScale": 1,
    "fromY": 0,
    "toY": 0,
    "fromX": 0,
    "toX": 0,
    "fromAngle": 0,
    "toAngle": 0,
    "fromAlpha": 1,
    "toAlpha": 1,
    "yoyo": false,
    "duration": 1,
    "keyTime": 0,
    "repeat": -1,
    "url": "fx_avatar.png"
  },
  {
    "id": 800,
    "nameKey": "fx_item",
    "aboveCharacter": false,
    "tint": 16777215,
    "frameRate": 1,
    "frameSize": 128,
    "bodySize": 128,
    "fromScale": 1,
    "toScale": 1,
    "fromY": 0,
    "toY": 0,
    "fromX": 0,
    "toX": 0,
    "fromAngle": 0,
    "toAngle": 0,
    "fromAlpha": 1,
    "toAlpha": 1,
    "yoyo": false,
    "duration": 0.5,
    "keyTime": 0.5,
    "repeat": -1,
    "url": "fx_item.png"
  },
  {
    "id": 801,
    "nameKey": "fx_item_01",
    "aboveCharacter": false,
    "tint": 16777215,
    "frameRate": 1,
    "frameSize": 128,
    "bodySize": 128,
    "fromScale": 0.5,
    "toScale": 0.5,
    "fromY": 0,
    "toY": 0,
    "fromX": 0,
    "toX": 0,
    "fromAngle": 0,
    "toAngle": 0,
    "fromAlpha": 1,
    "toAlpha": 1,
    "yoyo": false,
    "duration": 0.5,
    "keyTime": 0.5,
    "repeat": -1,
    "url": "fx_item_01.png"
  },
  {
    "id": 802,
    "nameKey": "fx_item_02",
    "aboveCharacter": false,
    "tint": 16777215,
    "frameRate": 1,
    "frameSize": 128,
    "bodySize": 128,
    "fromScale": 1,
    "toScale": 1,
    "fromY": 0,
    "toY": 0,
    "fromX": 0,
    "toX": 0,
    "fromAngle": -90,
    "toAngle": 270,
    "fromAlpha": 1,
    "toAlpha": 1,
    "yoyo": false,
    "duration": 0.5,
    "keyTime": 0.2,
    "repeat": 0,
    "url": "fx_item_02.png"
  },
  {
    "id": 803,
    "nameKey": "fx_item_03",
    "aboveCharacter": false,
    "tint": 16777215,
    "frameRate": 32,
    "frameSize": 219,
    "bodySize": 219,
    "fromScale": 1.2,
    "toScale": 1.2,
    "fromY": 0,
    "toY": 0,
    "fromX": 0,
    "toX": 0,
    "fromAngle": 0,
    "toAngle": 0,
    "fromAlpha": 1,
    "toAlpha": 1,
    "yoyo": false,
    "duration": 0.5,
    "keyTime": 0.1,
    "repeat": 0,
    "url": "fx_item_03.png"
  },
  {
    "id": 804,
    "nameKey": "fx_item_04",
    "aboveCharacter": false,
    "tint": 16777215,
    "frameRate": 70,
    "frameSize": 100,
    "bodySize": 100,
    "fromScale": 1,
    "toScale": 1,
    "fromY": 0,
    "toY": 0,
    "fromX": 0,
    "toX": 0,
    "fromAngle": 0,
    "toAngle": 0,
    "fromAlpha": 1,
    "toAlpha": 1,
    "yoyo": false,
    "duration": 0.3,
    "keyTime": 0.3,
    "repeat": 0,
    "url": "fx_item_04.png"
  }
]
